aaanalysis/__init__.py
aaanalysis/_data/__init__.py
aaanalysis/_data/benchmarks/AA_CASPASE3.tsv
aaanalysis/_data/benchmarks/AA_FURIN.tsv
aaanalysis/_data/benchmarks/AA_LDR.tsv
aaanalysis/_data/benchmarks/AA_MMP2.tsv
aaanalysis/_data/benchmarks/AA_RNABIND.tsv
aaanalysis/_data/benchmarks/AA_SA.tsv
aaanalysis/_data/benchmarks/DOM_GSEC.tsv
aaanalysis/_data/benchmarks/DOM_GSEC_PU.tsv
aaanalysis/_data/benchmarks/Overview.tsv
aaanalysis/_data/benchmarks/SEQ_AMYLO.tsv
aaanalysis/_data/benchmarks/SEQ_CAPSID.tsv
aaanalysis/_data/benchmarks/SEQ_DISULFIDE.tsv
aaanalysis/_data/benchmarks/SEQ_LOCATION.tsv
aaanalysis/_data/benchmarks/SEQ_SOLUBLE.tsv
aaanalysis/_data/benchmarks/SEQ_TAIL.tsv
aaanalysis/_data/features/FEATURES_DOM_GSEC.tsv
aaanalysis/_data/scales.tsv
aaanalysis/_data/scales_cat.tsv
aaanalysis/_data/scales_pc.tsv
aaanalysis/_data/scales_raw.tsv
aaanalysis/_data/top60.tsv
aaanalysis/_data/top60_eval.tsv
aaanalysis/_utils/__init__.py
aaanalysis/_utils/_utils.py
aaanalysis/_utils/check_data.py
aaanalysis/_utils/check_models.py
aaanalysis/_utils/check_plots.py
aaanalysis/_utils/check_type.py
aaanalysis/_utils/decorators.py
aaanalysis/_utils/metrics.py
aaanalysis/_utils/plotting.py
aaanalysis/_utils/utils_output.py
aaanalysis/_utils/utils_plot_elements.py
aaanalysis/_utils/utils_plot_parts.py
aaanalysis/_utils/utils_types.py
aaanalysis/config.py
aaanalysis/data_handling/__init__.py
aaanalysis/data_handling/_backend/__init__.py
aaanalysis/data_handling/_backend/parse_fasta.py
aaanalysis/data_handling/_backend/seq_preproc/__init__.py
aaanalysis/data_handling/_backend/seq_preproc/_utils.py
aaanalysis/data_handling/_backend/seq_preproc/encode_integer.py
aaanalysis/data_handling/_backend/seq_preproc/encode_one_hot.py
aaanalysis/data_handling/_backend/seq_preproc/get_aa_window.py
aaanalysis/data_handling/_backend/seq_preproc/get_sliding_aa_window.py
aaanalysis/data_handling/_load_dataset.py
aaanalysis/data_handling/_load_features.py
aaanalysis/data_handling/_load_scales.py
aaanalysis-1.0.2.dist-info/LICENSE
aaanalysis-1.0.2.dist-info/METADATA
aaanalysis-1.0.2.dist-info/WHEEL
aaanalysis-1.0.2.dist-info/RECORD
