Metadata-Version: 2.3
Name: aaanalysis
Version: 1.0.2
Summary: Python framework for interpretable protein prediction
License: BSD-3-Clause
Keywords: protein,prediction,bioinformatics,machine learning,interpretable AI
Author: Stephan Breimann
Author-email: stephanbreimann@gmail.de
Requires-Python: >=3.9,<3.13
Classifier: Development Status :: 5 - Production/Stable
Classifier: Intended Audience :: Developers
Classifier: Intended Audience :: Science/Research
Classifier: License :: OSI Approved :: BSD License
Classifier: License :: OSI Approved :: MIT License
Classifier: Natural Language :: English
Classifier: Operating System :: OS Independent
Classifier: Programming Language :: Python :: 3
Classifier: Programming Language :: Python :: 3.9
Classifier: Programming Language :: Python :: 3.10
Classifier: Programming Language :: Python :: 3.11
Classifier: Programming Language :: Python :: 3.12
Classifier: Topic :: Scientific/Engineering
Classifier: Topic :: Scientific/Engineering :: Artificial Intelligence
Classifier: Topic :: Scientific/Engineering :: Bio-Informatics
Provides-Extra: pro
Requires-Dist: Jinja2 (>=3.1.6,<4.0.0)
Requires-Dist: Pillow (>=11.1.0,<12.0.0)
Requires-Dist: UpSetPlot (>=0.9.0,<0.10.0) ; extra == "pro"
Requires-Dist: biopython (>=1.85,<2.0) ; extra == "pro"
Requires-Dist: cycler (>=0.12.1,<0.13.0)
Requires-Dist: et-xmlfile (>=2.0.0,<3.0.0)
Requires-Dist: fonttools (>=4.55.6,<5.0.0)
Requires-Dist: hypothesis (>=6.124.7,<7.0.0) ; extra == "pro"
Requires-Dist: ipython (>=8.18.1,<9.0.0) ; extra == "pro"
Requires-Dist: joblib (>=1.4.2,<2.0.0)
Requires-Dist: kiwisolver (>=1.4.7,<2.0.0)
Requires-Dist: logomaker (>=0.8.6,<0.9.0)
Requires-Dist: matplotlib (>=3.5.3,<=3.9.0)
Requires-Dist: numpy (>=1.24.4,<=2.1.3)
Requires-Dist: openpyxl (>=3.1.5,<4.0.0)
Requires-Dist: packaging (>=24.2,<25.0)
Requires-Dist: pandas (>=2.2.3,<3.0.0)
Requires-Dist: patsy (>=1.0.1,<2.0.0)
Requires-Dist: pip (>=25.0.0,<26.0.0)
Requires-Dist: pyparsing (>=3.2.1,<4.0.0)
Requires-Dist: pytest (>=8.3.4,<9.0.0) ; extra == "pro"
Requires-Dist: python-dateutil (>=2.9.0,<3.0.0)
Requires-Dist: pytz (>=2024.2,<2025.0)
Requires-Dist: scikit-learn (>=1.6.1,<2.0.0)
Requires-Dist: scipy (>=1.13.1,<2.0.0)
Requires-Dist: seaborn (>=0.13.2,<0.14.0)
Requires-Dist: shap (>=0.46.0,<0.47.0) ; extra == "pro"
Requires-Dist: six (>=1.17.0,<2.0.0)
Requires-Dist: threadpoolctl (>=3.5.0,<4.0.0)
Project-URL: Documentation, https://aaanalysis.readthedocs.io
Project-URL: Homepage, https://aaanalysis.readthedocs.io
Project-URL: Repository, https://github.com/breimanntools/aaanalysis
